{"type":"View","props":{"width":678,"height":865},"compId":2,"child":[{"type":"Image","props":{"y":25,"x":24,"width":631,"var":"bg1","skin":"remote/common/base/mb.png","sizeGrid":"18,21,22,19","height":837,"centerX":0},"compId":3},{"type":"Image","props":{"y":0,"x":589,"var":"close1","skin":"remote/common/base/close45.png"},"compId":4},{"type":"Image","props":{"y":49,"x":226,"width":227,"skin":"remote/common/base/sxk.png","sizeGrid":"0,24,0,24","height":55,"centerX":0},"compId":5},{"type":"Label","props":{"y":59,"x":269,"var":"tf2","text":"凶兽图鉴","fontSize":35,"font":"BOLD","color":"#BE8757","centerX":0},"compId":6},{"type":"Image","props":{"y":151,"x":92,"var":"bg2","skin":"remote/fighthard/az_bg1.png","centerX":0},"compId":7},{"type":"Image","props":{"y":117,"x":427,"var":"bg7","skin":"remote/zhengzhan/line.png"},"compId":8},{"type":"Image","props":{"y":117,"x":208,"var":"bg8","skin":"remote/zhengzhan/line.png","scaleX":-1},"compId":9},{"type":"Label","props":{"y":107,"x":299,"var":"nametf","text":"凶兽","strokeColor":"#6B280A","stroke":3,"fontSize":40,"color":"#F83535","centerX":0},"compId":10},{"type":"Sprite","props":{"y":398,"x":305,"var":"avatarCon"},"compId":11},{"type":"Label","props":{"y":415,"x":148,"width":383,"var":"tf3","text":"高闪避，回复克星","strokeColor":"#7E5236","stroke":3,"height":20,"fontSize":22,"font":"BOLD","color":"#F1E1C2","centerX":0,"align":"center"},"compId":12},{"type":"Image","props":{"y":467,"x":56,"width":566,"var":"bg3","skin":"remote/common/base/juxing_2.png","sizeGrid":"10,11,13,11","height":200,"centerX":0},"compId":13},{"type":"Label","props":{"y":476,"x":283,"var":"tf4","text":"凶兽技能","height":20,"fontSize":28,"font":"BOLD","color":"#B2713C","centerX":0,"align":"center"},"compId":14},{"type":"List","props":{"y":702,"x":77,"width":524,"var":"list1","spaceX":20,"height":125,"hScrollBarSkin":" ","centerX":0},"compId":15,"child":[{"type":"ui_fighthard_avatar","props":{"renderType":"render","runtime":"ui.views.fighthard.ui_fighthard_avatarUI"},"compId":17}]},{"type":"List","props":{"y":535,"x":57,"width":516,"var":"list2","spaceX":38,"height":100,"hScrollBarSkin":" "},"compId":16,"child":[{"type":"ui_fight_hard_cirle","props":{"renderType":"render","runtime":"ui.views.fighthard.ui_fight_hard_cirleUI"},"compId":18}]}],"loadList":["remote/common/base/mb.png","remote/common/base/close45.png","remote/common/base/sxk.png","remote/fighthard/az_bg1.png","remote/zhengzhan/line.png","remote/common/base/juxing_2.png","views/fighthard/ui_fighthard_avatar.scene"],"loadList3D":[]}