{"type":"View","props":{"width":750,"height":1334},"compId":2,"child":[{"type":"Sprite","props":{"width":750,"var":"succeed","height":1334},"compId":5,"child":[{"type":"Sprite","props":{"y":506,"x":367,"var":"effectCon"},"compId":16},{"type":"Sprite","props":{"y":564,"x":0,"texture":"remote/maoxian/dikuang.png"},"compId":6},{"type":"Label","props":{"y":556,"x":343,"var":"rewadTf","text":"奖励","fontSize":32,"font":"BOLD","color":"#f6b96a"},"compId":7},{"type":"Sprite","props":{"y":914,"x":367,"var":"rewardcontainer"},"compId":8},{"type":"Label","props":{"y":1081,"x":221,"var":"skip11","text":"点击空白位置返回主界面","strokeColor":"#94751C","stroke":2,"fontSize":28,"font":"BOLD","color":"#ffff99"},"compId":9},{"type":"Image","props":{"y":504,"skin":"remote/maoxian/shengliheng.png"},"compId":10},{"type":"Label","props":{"y":861,"x":343,"var":"harmtitle","text":"奖励","fontSize":32,"font":"BOLD","color":"#FFF08D"},"compId":11}]},{"type":"Sprite","props":{"width":750,"var":"fail","height":1334},"compId":19,"child":[{"type":"Sprite","props":{"y":290,"x":10,"texture":"remote/maoxian/dingkuang_1.png"},"compId":20},{"type":"Sprite","props":{"y":566,"x":10,"texture":"remote/maoxian/dikuang_1.png"},"compId":21},{"type":"Label","props":{"y":1081,"x":221,"var":"skipTf","text":"点击空白位置返回主界面","strokeColor":"#6D6D6D","stroke":2,"fontSize":28,"font":"BOLD","color":"#D1E5FF"},"compId":22}]},{"type":"Image","props":{"y":567,"x":260,"var":"img0","skin":"remote/jjc/vs.png"},"compId":15},{"type":"ui_score_jjc_item_view","props":{"y":619,"x":188,"var":"item0","runtime":"ui.views.jjc.ui_score_jjc_item_viewUI"},"compId":17},{"type":"ui_score_jjc_item_view","props":{"y":619,"x":467,"var":"item1","runtime":"ui.views.jjc.ui_score_jjc_item_viewUI"},"compId":18}],"loadList":["remote/maoxian/dikuang.png","remote/maoxian/shengliheng.png","remote/maoxian/dingkuang_1.png","remote/maoxian/dikuang_1.png","remote/jjc/vs.png","views/jjc/ui_score_jjc_item_view.scene"],"loadList3D":[]}