{"type":"View","props":{"width":709,"height":1170},"compId":2,"child":[{"type":"Sprite","props":{"y":9,"x":0.5,"texture":"remote/drawEvent/cxyxn_bg.png"},"compId":4},{"type":"Image","props":{"y":15,"x":587,"var":"btn_tip","skin":"remote/common/base/zqyh_gantanhao.png"},"compId":40},{"type":"Image","props":{"y":0,"x":648,"var":"btn_close","skin":"remote/drawEvent/x.png"},"compId":5},{"type":"Sprite","props":{"y":126,"x":2,"var":"sp1"},"compId":36,"child":[{"type":"Label","props":{"x":180,"text":"活动剩余时间：","strokeColor":"#7C430C","fontSize":20,"font":"BOLD","color":"#FCEEC7","align":"left"},"compId":6},{"type":"Label","props":{"x":320,"width":235,"var":"lab_time","text":"3天","strokeColor":"#7C430C","height":20,"fontSize":20,"font":"BOLD","color":"#FCEEC7","align":"left"},"compId":7},{"type":"Sprite","props":{"y":28,"x":576,"var":"spIcon","texture":"remote/drawEvent/ljjl.png"},"compId":8,"child":[{"type":"Label","props":{"y":4,"x":13,"text":"累计奖励","strokeColor":"#7C430C","fontSize":20,"font":"BOLD","color":"#FCEEC7","align":"left"},"compId":9},{"type":"Image","props":{"y":28,"x":10,"var":"icon","skin":"o/icon/1.png","scaleY":1,"scaleX":1},"compId":24},{"type":"Label","props":{"y":93,"x":10,"width":93,"var":"lab_num","text":"50","strokeColor":"#90501F","stroke":2,"fontSize":22,"font":"BOLD","color":"#FFFCEA","align":"right"},"compId":25},{"type":"Label","props":{"y":120,"x":10,"width":87,"var":"lab_num1","text":"2/50","strokeColor":"#7C430C","height":20,"fontSize":20,"font":"BOLD","color":"#A12B2D","align":"center"},"compId":11},{"type":"Image","props":{"y":39.5,"x":13,"var":"gouImg","skin":"remote/common/base/fj_dg_0.png"},"compId":58}]},{"type":"Label","props":{"y":741,"x":17,"text":"福运值","strokeColor":"#90501F","stroke":2,"fontSize":24,"font":"BOLD","color":"#FFFCEA","align":"left"},"compId":12},{"type":"Image","props":{"y":742,"x":100,"width":578,"skin":"remote/drawEvent/jyt.png","sizeGrid":"0,19,0,17","height":21},"compId":13,"child":[{"type":"Image","props":{"y":1,"x":2,"width":575,"var":"pro","skin":"remote/drawEvent/jyt_1.png","sizeGrid":"0,17,0,17","height":19},"compId":14}]},{"type":"Label","props":{"y":742,"x":107,"width":509,"var":"lab_pro","text":"0/180","strokeColor":"#90501F","stroke":2,"height":20,"fontSize":20,"font":"BOLD","color":"#FFFCEA","align":"center"},"compId":15},{"type":"Image","props":{"y":782,"x":292,"width":123,"skin":"remote/drawEvent/gh.png","sizeGrid":"0,21,0,17","height":24},"compId":17},{"type":"Image","props":{"y":767,"x":275,"var":"img","skin":"o/icon/1.png","scaleY":0.6,"scaleX":0.6},"compId":16},{"type":"Image","props":{"y":818,"x":257,"var":"btn","skin":"remote/drawEvent/qf_anniu.png"},"compId":19},{"type":"Label","props":{"y":780,"x":320,"width":72,"var":"lab_count","text":"999","strokeColor":"#90501F","stroke":2,"fontSize":26,"font":"BOLD","color":"#FFFCEA","align":"center"},"compId":20},{"type":"Label","props":{"y":897,"x":328,"text":"连抽十次","strokeColor":"#90501f","fontSize":22,"font":"BOLD","color":"#AD6E36","align":"left"},"compId":21},{"type":"Image","props":{"y":889,"x":290,"width":33,"var":"ckbg","skin":"remote/common/base/duigoukuang.png","sizeGrid":"12,12,12,12","height":33},"compId":22,"child":[{"type":"Image","props":{"y":-2,"x":5,"var":"gou","skin":"remote/common/base/duigou.png"},"compId":23}]},{"type":"Sprite","props":{"y":33},"compId":35,"child":[{"type":"ui_DrawEventItem","props":{"x":236,"var":"item","runtime":"ui.views.drawEvent.ui_DrawEventItemUI"},"compId":26},{"type":"ui_DrawEventItem","props":{"y":91,"x":52,"var":"item1","scaleY":0.7,"scaleX":0.7,"runtime":"ui.views.drawEvent.ui_DrawEventItemUI"},"compId":27},{"type":"ui_DrawEventItem","props":{"y":148,"x":492,"var":"item2","scaleY":0.7,"scaleX":0.7,"runtime":"ui.views.drawEvent.ui_DrawEventItemUI"},"compId":28},{"type":"ui_DrawEventItem","props":{"y":266,"x":183,"var":"item3","scaleY":0.7,"scaleX":0.7,"runtime":"ui.views.drawEvent.ui_DrawEventItemUI"},"compId":29},{"type":"ui_DrawEventItem","props":{"y":349,"var":"item4","scaleY":0.7,"scaleX":0.7,"runtime":"ui.views.drawEvent.ui_DrawEventItemUI"},"compId":30},{"type":"ui_DrawEventItem","props":{"y":428,"x":291,"var":"item5","scaleY":0.7,"scaleX":0.7,"runtime":"ui.views.drawEvent.ui_DrawEventItemUI"},"compId":31},{"type":"ui_DrawEventItem","props":{"y":368,"x":544,"var":"item6","scaleY":0.7,"scaleX":0.7,"runtime":"ui.views.drawEvent.ui_DrawEventItemUI"},"compId":32},{"type":"ui_DrawEventItem","props":{"y":521,"x":127,"var":"item7","scaleY":0.7,"scaleX":0.7,"runtime":"ui.views.drawEvent.ui_DrawEventItemUI"},"compId":33},{"type":"ui_DrawEventItem","props":{"y":524,"x":433,"var":"item8","scaleY":0.7,"scaleX":0.7,"runtime":"ui.views.drawEvent.ui_DrawEventItemUI"},"compId":34},{"type":"Image","props":{"y":-8,"x":16,"var":"btn_award","skin":"remote/drawEvent/ckjp.png"},"compId":59}]},{"type":"Image","props":{"y":207,"x":322,"var":"sp_click","skin":"remote/drawEvent/gh.png"},"compId":54,"child":[{"type":"Label","props":{"y":3,"x":11,"text":"更换","strokeColor":"#7C430C","fontSize":18,"font":"BOLD","color":"#FCEEC7","align":"left"},"compId":55}]}]},{"type":"Sprite","props":{"y":127,"x":43,"var":"sp2"},"compId":46,"child":[{"type":"Label","props":{"x":141,"text":"重置剩余时间：","strokeColor":"#7C430C","fontSize":20,"font":"BOLD","color":"#FCEEC7","align":"left"},"compId":41},{"type":"Label","props":{"x":281,"width":235,"var":"lab_time1","text":"3天","strokeColor":"#7C430C","height":20,"fontSize":20,"font":"BOLD","color":"#FCEEC7","align":"left"},"compId":42},{"type":"List","props":{"y":40,"width":626,"var":"list","vScrollBarSkin":" ","spaceY":15,"repeatY":6,"repeatX":1,"height":906},"compId":44,"child":[{"type":"ui_DrawEventLBItem","props":{"renderType":"render","runtime":"ui.views.drawEvent.ui_DrawEventLBItemUI"},"compId":45}]}]},{"type":"Sprite","props":{"y":127,"x":42,"var":"sp3"},"compId":52,"child":[{"type":"Label","props":{"x":141,"text":"重置剩余时间：","strokeColor":"#7C430C","fontSize":20,"font":"BOLD","color":"#FCEEC7","align":"left"},"compId":47},{"type":"Label","props":{"x":281,"width":235,"var":"lab_time2","text":"3天","strokeColor":"#7C430C","height":20,"fontSize":20,"font":"BOLD","color":"#FCEEC7","align":"left"},"compId":48},{"type":"List","props":{"y":40,"width":626,"var":"list1","vScrollBarSkin":" ","spaceY":15,"repeatY":7,"repeatX":1,"height":906},"compId":49,"child":[{"type":"ui_DrawEventTaskItem","props":{"renderType":"render","runtime":"ui.views.drawEvent.ui_DrawEventTaskItemUI"},"compId":51}]}]},{"type":"ui_tab","props":{"y":1075,"x":0,"var":"tab1","runtime":"ui.views.drawEvent.ui_tabUI"},"compId":37},{"type":"ui_tab","props":{"y":1075,"x":235,"var":"tab2","runtime":"ui.views.drawEvent.ui_tabUI"},"compId":38},{"type":"ui_tab","props":{"y":1075,"x":471,"var":"tab3","runtime":"ui.views.drawEvent.ui_tabUI"},"compId":39}],"loadList":["remote/drawEvent/cxyxn_bg.png","remote/common/base/zqyh_gantanhao.png","remote/drawEvent/x.png","remote/drawEvent/ljjl.png","o/icon/1.png","remote/common/base/fj_dg_0.png","remote/drawEvent/jyt.png","remote/drawEvent/jyt_1.png","remote/drawEvent/gh.png","remote/drawEvent/qf_anniu.png","remote/common/base/duigoukuang.png","remote/common/base/duigou.png","views/drawEvent/ui_DrawEventItem.scene","remote/drawEvent/ckjp.png","views/drawEvent/ui_DrawEventLBItem.scene","views/drawEvent/ui_DrawEventTaskItem.scene","views/drawEvent/ui_tab.scene"],"loadList3D":[]}