{"mDataMap":{"1":{"f_id":1,"f_FacilityRank":0,"f_FacilityLevel":0,"f_LanternAttribute":"20011:200","f_UpgradeCost":"22-1","f_Task":""},"2":{"f_id":2,"f_FacilityRank":0,"f_FacilityLevel":1,"f_LanternAttribute":"20011:400","f_UpgradeCost":"22-2","f_Task":""},"3":{"f_id":3,"f_FacilityRank":0,"f_FacilityLevel":2,"f_LanternAttribute":"20011:600","f_UpgradeCost":"22-3","f_Task":""},"4":{"f_id":4,"f_FacilityRank":0,"f_FacilityLevel":3,"f_LanternAttribute":"20011:800","f_UpgradeCost":"22-4","f_Task":""},"5":{"f_id":5,"f_FacilityRank":0,"f_FacilityLevel":4,"f_LanternAttribute":"20011:1000","f_UpgradeCost":"22-5","f_Task":""},"6":{"f_id":6,"f_FacilityRank":0,"f_FacilityLevel":5,"f_LanternAttribute":"20011:1200","f_UpgradeCost":"22-6","f_Task":"4-5"},"7":{"f_id":7,"f_FacilityRank":1,"f_FacilityLevel":0,"f_LanternAttribute":"20011:1400","f_UpgradeCost":"22-2","f_Task":""},"8":{"f_id":8,"f_FacilityRank":1,"f_FacilityLevel":1,"f_LanternAttribute":"20011:1600","f_UpgradeCost":"22-3","f_Task":""},"9":{"f_id":9,"f_FacilityRank":1,"f_FacilityLevel":2,"f_LanternAttribute":"20011:1800","f_UpgradeCost":"22-4","f_Task":""},"10":{"f_id":10,"f_FacilityRank":1,"f_FacilityLevel":3,"f_LanternAttribute":"20011:2000","f_UpgradeCost":"22-5","f_Task":""},"11":{"f_id":11,"f_FacilityRank":1,"f_FacilityLevel":4,"f_LanternAttribute":"20011:2200","f_UpgradeCost":"22-6","f_Task":""},"12":{"f_id":12,"f_FacilityRank":1,"f_FacilityLevel":5,"f_LanternAttribute":"20011:2400","f_UpgradeCost":"22-7","f_Task":""},"13":{"f_id":13,"f_FacilityRank":1,"f_FacilityLevel":6,"f_LanternAttribute":"20011:2600","f_UpgradeCost":"22-8","f_Task":""},"14":{"f_id":14,"f_FacilityRank":1,"f_FacilityLevel":7,"f_LanternAttribute":"20011:2800","f_UpgradeCost":"22-9","f_Task":""},"15":{"f_id":15,"f_FacilityRank":1,"f_FacilityLevel":8,"f_LanternAttribute":"20011:3000","f_UpgradeCost":"22-10","f_Task":""},"16":{"f_id":16,"f_FacilityRank":1,"f_FacilityLevel":9,"f_LanternAttribute":"20011:3200","f_UpgradeCost":"22-11","f_Task":""},"17":{"f_id":17,"f_FacilityRank":1,"f_FacilityLevel":10,"f_LanternAttribute":"20011:3400","f_UpgradeCost":"22-12","f_Task":"4-10"},"18":{"f_id":18,"f_FacilityRank":2,"f_FacilityLevel":0,"f_LanternAttribute":"20011:3600","f_UpgradeCost":"22-3","f_Task":""},"19":{"f_id":19,"f_FacilityRank":2,"f_FacilityLevel":1,"f_LanternAttribute":"20011:3800","f_UpgradeCost":"22-4","f_Task":""},"20":{"f_id":20,"f_FacilityRank":2,"f_FacilityLevel":2,"f_LanternAttribute":"20011:4000","f_UpgradeCost":"22-5","f_Task":""},"21":{"f_id":21,"f_FacilityRank":2,"f_FacilityLevel":3,"f_LanternAttribute":"20011:4200","f_UpgradeCost":"22-6","f_Task":""},"22":{"f_id":22,"f_FacilityRank":2,"f_FacilityLevel":4,"f_LanternAttribute":"20011:4400","f_UpgradeCost":"22-7","f_Task":""},"23":{"f_id":23,"f_FacilityRank":2,"f_FacilityLevel":5,"f_LanternAttribute":"20011:4600","f_UpgradeCost":"22-8","f_Task":""},"24":{"f_id":24,"f_FacilityRank":2,"f_FacilityLevel":6,"f_LanternAttribute":"20011:4800","f_UpgradeCost":"22-9","f_Task":""},"25":{"f_id":25,"f_FacilityRank":2,"f_FacilityLevel":7,"f_LanternAttribute":"20011:5000","f_UpgradeCost":"22-10","f_Task":""},"26":{"f_id":26,"f_FacilityRank":2,"f_FacilityLevel":8,"f_LanternAttribute":"20011:5200","f_UpgradeCost":"22-11","f_Task":""},"27":{"f_id":27,"f_FacilityRank":2,"f_FacilityLevel":9,"f_LanternAttribute":"20011:5400","f_UpgradeCost":"22-12","f_Task":""},"28":{"f_id":28,"f_FacilityRank":2,"f_FacilityLevel":10,"f_LanternAttribute":"20011:5600","f_UpgradeCost":"22-13","f_Task":""},"29":{"f_id":29,"f_FacilityRank":2,"f_FacilityLevel":11,"f_LanternAttribute":"20011:5800","f_UpgradeCost":"22-14","f_Task":""},"30":{"f_id":30,"f_FacilityRank":2,"f_FacilityLevel":12,"f_LanternAttribute":"20011:6000","f_UpgradeCost":"22-15","f_Task":""},"31":{"f_id":31,"f_FacilityRank":2,"f_FacilityLevel":13,"f_LanternAttribute":"20011:6200","f_UpgradeCost":"22-16","f_Task":""},"32":{"f_id":32,"f_FacilityRank":2,"f_FacilityLevel":14,"f_LanternAttribute":"20011:6400","f_UpgradeCost":"22-17","f_Task":""},"33":{"f_id":33,"f_FacilityRank":2,"f_FacilityLevel":15,"f_LanternAttribute":"20011:6600","f_UpgradeCost":"22-18","f_Task":""},"34":{"f_id":34,"f_FacilityRank":2,"f_FacilityLevel":16,"f_LanternAttribute":"20011:6800","f_UpgradeCost":"22-19","f_Task":""},"35":{"f_id":35,"f_FacilityRank":2,"f_FacilityLevel":17,"f_LanternAttribute":"20011:7000","f_UpgradeCost":"22-20","f_Task":""},"36":{"f_id":36,"f_FacilityRank":2,"f_FacilityLevel":18,"f_LanternAttribute":"20011:7200","f_UpgradeCost":"22-21","f_Task":""},"37":{"f_id":37,"f_FacilityRank":2,"f_FacilityLevel":19,"f_LanternAttribute":"20011:7400","f_UpgradeCost":"22-22","f_Task":""},"38":{"f_id":38,"f_FacilityRank":2,"f_FacilityLevel":20,"f_LanternAttribute":"20011:7600","f_UpgradeCost":"22-23","f_Task":"4-20"},"39":{"f_id":39,"f_FacilityRank":3,"f_FacilityLevel":0,"f_LanternAttribute":"20011:7800","f_UpgradeCost":"22-4","f_Task":""},"40":{"f_id":40,"f_FacilityRank":3,"f_FacilityLevel":1,"f_LanternAttribute":"20011:8000","f_UpgradeCost":"22-5","f_Task":""},"41":{"f_id":41,"f_FacilityRank":3,"f_FacilityLevel":2,"f_LanternAttribute":"20011:8200","f_UpgradeCost":"22-6","f_Task":""},"42":{"f_id":42,"f_FacilityRank":3,"f_FacilityLevel":3,"f_LanternAttribute":"20011:8400","f_UpgradeCost":"22-7","f_Task":""},"43":{"f_id":43,"f_FacilityRank":3,"f_FacilityLevel":4,"f_LanternAttribute":"20011:8600","f_UpgradeCost":"22-8","f_Task":""},"44":{"f_id":44,"f_FacilityRank":3,"f_FacilityLevel":5,"f_LanternAttribute":"20011:8800","f_UpgradeCost":"22-9","f_Task":""},"45":{"f_id":45,"f_FacilityRank":3,"f_FacilityLevel":6,"f_LanternAttribute":"20011:9000","f_UpgradeCost":"22-10","f_Task":""},"46":{"f_id":46,"f_FacilityRank":3,"f_FacilityLevel":7,"f_LanternAttribute":"20011:9200","f_UpgradeCost":"22-11","f_Task":""},"47":{"f_id":47,"f_FacilityRank":3,"f_FacilityLevel":8,"f_LanternAttribute":"20011:9400","f_UpgradeCost":"22-12","f_Task":""},"48":{"f_id":48,"f_FacilityRank":3,"f_FacilityLevel":9,"f_LanternAttribute":"20011:9600","f_UpgradeCost":"22-13","f_Task":""},"49":{"f_id":49,"f_FacilityRank":3,"f_FacilityLevel":10,"f_LanternAttribute":"20011:9800","f_UpgradeCost":"22-14","f_Task":""},"50":{"f_id":50,"f_FacilityRank":3,"f_FacilityLevel":11,"f_LanternAttribute":"20011:10000","f_UpgradeCost":"22-15","f_Task":""},"51":{"f_id":51,"f_FacilityRank":3,"f_FacilityLevel":12,"f_LanternAttribute":"20011:10200","f_UpgradeCost":"22-16","f_Task":""},"52":{"f_id":52,"f_FacilityRank":3,"f_FacilityLevel":13,"f_LanternAttribute":"20011:10400","f_UpgradeCost":"22-17","f_Task":""},"53":{"f_id":53,"f_FacilityRank":3,"f_FacilityLevel":14,"f_LanternAttribute":"20011:10600","f_UpgradeCost":"22-18","f_Task":""},"54":{"f_id":54,"f_FacilityRank":3,"f_FacilityLevel":15,"f_LanternAttribute":"20011:10800","f_UpgradeCost":"22-19","f_Task":""},"55":{"f_id":55,"f_FacilityRank":3,"f_FacilityLevel":16,"f_LanternAttribute":"20011:11000","f_UpgradeCost":"22-20","f_Task":""},"56":{"f_id":56,"f_FacilityRank":3,"f_FacilityLevel":17,"f_LanternAttribute":"20011:11200","f_UpgradeCost":"22-21","f_Task":""},"57":{"f_id":57,"f_FacilityRank":3,"f_FacilityLevel":18,"f_LanternAttribute":"20011:11400","f_UpgradeCost":"22-22","f_Task":""},"58":{"f_id":58,"f_FacilityRank":3,"f_FacilityLevel":19,"f_LanternAttribute":"20011:11600","f_UpgradeCost":"22-23","f_Task":""},"59":{"f_id":59,"f_FacilityRank":3,"f_FacilityLevel":20,"f_LanternAttribute":"20011:11800","f_UpgradeCost":"22-24","f_Task":""},"60":{"f_id":60,"f_FacilityRank":3,"f_FacilityLevel":21,"f_LanternAttribute":"20011:12000","f_UpgradeCost":"22-25","f_Task":""},"61":{"f_id":61,"f_FacilityRank":3,"f_FacilityLevel":22,"f_LanternAttribute":"20011:12200","f_UpgradeCost":"22-26","f_Task":""},"62":{"f_id":62,"f_FacilityRank":3,"f_FacilityLevel":23,"f_LanternAttribute":"20011:12400","f_UpgradeCost":"22-27","f_Task":""},"63":{"f_id":63,"f_FacilityRank":3,"f_FacilityLevel":24,"f_LanternAttribute":"20011:12600","f_UpgradeCost":"22-28","f_Task":""},"64":{"f_id":64,"f_FacilityRank":3,"f_FacilityLevel":25,"f_LanternAttribute":"20011:12800","f_UpgradeCost":"22-29","f_Task":"4-40"},"65":{"f_id":65,"f_FacilityRank":4,"f_FacilityLevel":0,"f_LanternAttribute":"20011:13000","f_UpgradeCost":"22-5","f_Task":""},"66":{"f_id":66,"f_FacilityRank":4,"f_FacilityLevel":1,"f_LanternAttribute":"20011:13200","f_UpgradeCost":"22-6","f_Task":""},"67":{"f_id":67,"f_FacilityRank":4,"f_FacilityLevel":2,"f_LanternAttribute":"20011:13400","f_UpgradeCost":"22-7","f_Task":""},"68":{"f_id":68,"f_FacilityRank":4,"f_FacilityLevel":3,"f_LanternAttribute":"20011:13600","f_UpgradeCost":"22-8","f_Task":""},"69":{"f_id":69,"f_FacilityRank":4,"f_FacilityLevel":4,"f_LanternAttribute":"20011:13800","f_UpgradeCost":"22-9","f_Task":""},"70":{"f_id":70,"f_FacilityRank":4,"f_FacilityLevel":5,"f_LanternAttribute":"20011:14000","f_UpgradeCost":"22-10","f_Task":""},"71":{"f_id":71,"f_FacilityRank":4,"f_FacilityLevel":6,"f_LanternAttribute":"20011:14200","f_UpgradeCost":"22-11","f_Task":""},"72":{"f_id":72,"f_FacilityRank":4,"f_FacilityLevel":7,"f_LanternAttribute":"20011:14400","f_UpgradeCost":"22-12","f_Task":""},"73":{"f_id":73,"f_FacilityRank":4,"f_FacilityLevel":8,"f_LanternAttribute":"20011:14600","f_UpgradeCost":"22-13","f_Task":""},"74":{"f_id":74,"f_FacilityRank":4,"f_FacilityLevel":9,"f_LanternAttribute":"20011:14800","f_UpgradeCost":"22-14","f_Task":""},"75":{"f_id":75,"f_FacilityRank":4,"f_FacilityLevel":10,"f_LanternAttribute":"20011:15000","f_UpgradeCost":"22-15","f_Task":""},"76":{"f_id":76,"f_FacilityRank":4,"f_FacilityLevel":11,"f_LanternAttribute":"20011:15200","f_UpgradeCost":"22-16","f_Task":""},"77":{"f_id":77,"f_FacilityRank":4,"f_FacilityLevel":12,"f_LanternAttribute":"20011:15400","f_UpgradeCost":"22-17","f_Task":""},"78":{"f_id":78,"f_FacilityRank":4,"f_FacilityLevel":13,"f_LanternAttribute":"20011:15600","f_UpgradeCost":"22-18","f_Task":""},"79":{"f_id":79,"f_FacilityRank":4,"f_FacilityLevel":14,"f_LanternAttribute":"20011:15800","f_UpgradeCost":"22-19","f_Task":""},"80":{"f_id":80,"f_FacilityRank":4,"f_FacilityLevel":15,"f_LanternAttribute":"20011:16000","f_UpgradeCost":"22-20","f_Task":""},"81":{"f_id":81,"f_FacilityRank":4,"f_FacilityLevel":16,"f_LanternAttribute":"20011:16200","f_UpgradeCost":"22-21","f_Task":""},"82":{"f_id":82,"f_FacilityRank":4,"f_FacilityLevel":17,"f_LanternAttribute":"20011:16400","f_UpgradeCost":"22-22","f_Task":""},"83":{"f_id":83,"f_FacilityRank":4,"f_FacilityLevel":18,"f_LanternAttribute":"20011:16600","f_UpgradeCost":"22-23","f_Task":""},"84":{"f_id":84,"f_FacilityRank":4,"f_FacilityLevel":19,"f_LanternAttribute":"20011:16800","f_UpgradeCost":"22-24","f_Task":""},"85":{"f_id":85,"f_FacilityRank":4,"f_FacilityLevel":20,"f_LanternAttribute":"20011:17000","f_UpgradeCost":"22-25","f_Task":""},"86":{"f_id":86,"f_FacilityRank":4,"f_FacilityLevel":21,"f_LanternAttribute":"20011:17200","f_UpgradeCost":"22-26","f_Task":""},"87":{"f_id":87,"f_FacilityRank":4,"f_FacilityLevel":22,"f_LanternAttribute":"20011:17400","f_UpgradeCost":"22-27","f_Task":""},"88":{"f_id":88,"f_FacilityRank":4,"f_FacilityLevel":23,"f_LanternAttribute":"20011:17600","f_UpgradeCost":"22-28","f_Task":""},"89":{"f_id":89,"f_FacilityRank":4,"f_FacilityLevel":24,"f_LanternAttribute":"20011:17800","f_UpgradeCost":"22-29","f_Task":""},"90":{"f_id":90,"f_FacilityRank":4,"f_FacilityLevel":25,"f_LanternAttribute":"20011:18000","f_UpgradeCost":"22-30","f_Task":""}}}