{"mDataMap":{"1":{"f_id":1,"f_HeroID":1,"f_name":"吕布","f_Region":6,"f_HeroQuality":6,"f_HeroType":1,"f_HeroCountry":4,"f_Attribute":"10004:3200|10005:1000","f_TokenID":45,"f_knowledge":"21-90","f_iconid":81,"f_info":""},"2":{"f_id":2,"f_HeroID":2,"f_name":"姜维","f_Region":7,"f_HeroQuality":6,"f_HeroType":1,"f_HeroCountry":1,"f_Attribute":"10003:15000|10004:2800","f_TokenID":41,"f_knowledge":"21-90","f_iconid":42,"f_info":""},"3":{"f_id":3,"f_HeroID":3,"f_name":"关羽","f_Region":4,"f_HeroQuality":5,"f_HeroType":1,"f_HeroCountry":1,"f_Attribute":"10004:2600|10004:1000","f_TokenID":0,"f_knowledge":"21-70","f_iconid":98,"f_info":""},"4":{"f_id":4,"f_HeroID":4,"f_name":"张飞","f_Region":4,"f_HeroQuality":5,"f_HeroType":1,"f_HeroCountry":1,"f_Attribute":"10003:10000|10004:2000","f_TokenID":0,"f_knowledge":"21-70","f_iconid":75,"f_info":""},"5":{"f_id":5,"f_HeroID":5,"f_name":"赵云","f_Region":4,"f_HeroQuality":5,"f_HeroType":1,"f_HeroCountry":1,"f_Attribute":"10004:2200|10005:900","f_TokenID":0,"f_knowledge":"21-70","f_iconid":36,"f_info":""},"6":{"f_id":6,"f_HeroID":6,"f_name":"黄忠","f_Region":1,"f_HeroQuality":5,"f_HeroType":1,"f_HeroCountry":1,"f_Attribute":"10003:8000|10004:2300","f_TokenID":0,"f_knowledge":"21-70","f_iconid":13,"f_info":""},"7":{"f_id":7,"f_HeroID":7,"f_name":"马超","f_Region":7,"f_HeroQuality":5,"f_HeroType":1,"f_HeroCountry":1,"f_Attribute":"10002:300|10003:13000","f_TokenID":0,"f_knowledge":"21-70","f_iconid":78,"f_info":""},"8":{"f_id":8,"f_HeroID":8,"f_name":"孙策","f_Region":2,"f_HeroQuality":5,"f_HeroType":1,"f_HeroCountry":1,"f_Attribute":"10005:700|10004:2200","f_TokenID":0,"f_knowledge":"21-70","f_iconid":105,"f_info":""},"9":{"f_id":9,"f_HeroID":9,"f_name":"许褚","f_Region":3,"f_HeroQuality":5,"f_HeroType":1,"f_HeroCountry":1,"f_Attribute":"10003:13000|10005:700","f_TokenID":0,"f_knowledge":"21-70","f_iconid":21,"f_info":""},"10":{"f_id":10,"f_HeroID":10,"f_name":"颜良","f_Region":6,"f_HeroQuality":5,"f_HeroType":1,"f_HeroCountry":1,"f_Attribute":"10004:2400|10005:400","f_TokenID":0,"f_knowledge":"21-70","f_iconid":85,"f_info":""},"11":{"f_id":11,"f_HeroID":11,"f_name":"文丑","f_Region":6,"f_HeroQuality":5,"f_HeroType":1,"f_HeroCountry":1,"f_Attribute":"10004:2000|10005:700","f_TokenID":0,"f_knowledge":"21-70","f_iconid":89,"f_info":""},"12":{"f_id":12,"f_HeroID":12,"f_name":"张辽","f_Region":5,"f_HeroQuality":5,"f_HeroType":1,"f_HeroCountry":1,"f_Attribute":"10005:800|10003:10000","f_TokenID":0,"f_knowledge":"21-70","f_iconid":103,"f_info":""},"13":{"f_id":13,"f_HeroID":13,"f_name":"庞德","f_Region":7,"f_HeroQuality":4,"f_HeroType":1,"f_HeroCountry":1,"f_Attribute":"10003:7600|10004:2000","f_TokenID":0,"f_knowledge":"21-50","f_iconid":33,"f_info":""},"14":{"f_id":14,"f_HeroID":14,"f_name":"张郃","f_Region":6,"f_HeroQuality":4,"f_HeroType":1,"f_HeroCountry":1,"f_Attribute":"10004:2000|10005:650","f_TokenID":0,"f_knowledge":"21-50","f_iconid":4,"f_info":""},"15":{"f_id":15,"f_HeroID":15,"f_name":"韩遂","f_Region":7,"f_HeroQuality":4,"f_HeroType":1,"f_HeroCountry":1,"f_Attribute":"10005:650|10003:7600","f_TokenID":0,"f_knowledge":"21-50","f_iconid":27,"f_info":""},"16":{"f_id":16,"f_HeroID":16,"f_name":"甘宁","f_Region":2,"f_HeroQuality":3,"f_HeroType":1,"f_HeroCountry":1,"f_Attribute":"10003:7000|10004:1700","f_TokenID":0,"f_knowledge":"21-20","f_iconid":84,"f_info":""},"17":{"f_id":17,"f_HeroID":17,"f_name":"典韦","f_Region":3,"f_HeroQuality":3,"f_HeroType":1,"f_HeroCountry":1,"f_Attribute":"10004:2000|10003:6450","f_TokenID":0,"f_knowledge":"21-20","f_iconid":82,"f_info":""},"18":{"f_id":18,"f_HeroID":18,"f_name":"夏侯渊","f_Region":3,"f_HeroQuality":3,"f_HeroType":1,"f_HeroCountry":1,"f_Attribute":"10002:260|10002:130","f_TokenID":0,"f_knowledge":"21-20","f_iconid":44,"f_info":""},"19":{"f_id":19,"f_HeroID":19,"f_name":"夏侯惇","f_Region":3,"f_HeroQuality":3,"f_HeroType":1,"f_HeroCountry":1,"f_Attribute":"10004:1700|10004:850","f_TokenID":0,"f_knowledge":"21-20","f_iconid":41,"f_info":""},"20":{"f_id":20,"f_HeroID":20,"f_name":"太史慈","f_Region":2,"f_HeroQuality":3,"f_HeroType":1,"f_HeroCountry":1,"f_Attribute":"10004:1900|10002:260","f_TokenID":0,"f_knowledge":"21-20","f_iconid":96,"f_info":""},"21":{"f_id":21,"f_HeroID":21,"f_name":"华雄","f_Region":5,"f_HeroQuality":3,"f_HeroType":1,"f_HeroCountry":1,"f_Attribute":"10004:1500|10005:550","f_TokenID":0,"f_knowledge":"21-20","f_iconid":104,"f_info":""},"22":{"f_id":22,"f_HeroID":22,"f_name":"严颜","f_Region":1,"f_HeroQuality":3,"f_HeroType":1,"f_HeroCountry":1,"f_Attribute":"10002:260|10005:700","f_TokenID":0,"f_knowledge":"21-20","f_iconid":94,"f_info":""},"23":{"f_id":23,"f_HeroID":23,"f_name":"王双","f_Region":1,"f_HeroQuality":3,"f_HeroType":1,"f_HeroCountry":1,"f_Attribute":"10003:6450|10005:700","f_TokenID":0,"f_knowledge":"21-20","f_iconid":24,"f_info":""},"24":{"f_id":24,"f_HeroID":24,"f_name":"张任","f_Region":1,"f_HeroQuality":3,"f_HeroType":1,"f_HeroCountry":1,"f_Attribute":"10004:1700|10005:600","f_TokenID":0,"f_knowledge":"21-20","f_iconid":23,"f_info":""},"25":{"f_id":25,"f_HeroID":25,"f_name":"徐晃","f_Region":3,"f_HeroQuality":2,"f_HeroType":1,"f_HeroCountry":1,"f_Attribute":"10003:5500|10004:1500","f_TokenID":0,"f_knowledge":"21-10","f_iconid":97,"f_info":""},"26":{"f_id":26,"f_HeroID":26,"f_name":"黄盖","f_Region":2,"f_HeroQuality":2,"f_HeroType":1,"f_HeroCountry":1,"f_Attribute":"10004:1500|10003:5500","f_TokenID":0,"f_knowledge":"21-10","f_iconid":14,"f_info":""},"27":{"f_id":27,"f_HeroID":27,"f_name":"马岱","f_Region":7,"f_HeroQuality":2,"f_HeroType":1,"f_HeroCountry":1,"f_Attribute":"10005:500|10005:500","f_TokenID":0,"f_knowledge":"21-10","f_iconid":6,"f_info":""},"28":{"f_id":28,"f_HeroID":28,"f_name":"貂蝉","f_Region":5,"f_HeroQuality":6,"f_HeroType":2,"f_HeroCountry":1,"f_Attribute":"10014:800|10016:800","f_TokenID":42,"f_knowledge":"21-90","f_iconid":60,"f_info":""},"29":{"f_id":29,"f_HeroID":29,"f_name":"甄姬","f_Region":3,"f_HeroQuality":5,"f_HeroType":2,"f_HeroCountry":1,"f_Attribute":"10017:500|10015:500","f_TokenID":0,"f_knowledge":"21-70","f_iconid":52,"f_info":""},"30":{"f_id":30,"f_HeroID":30,"f_name":"伏皇后","f_Region":5,"f_HeroQuality":5,"f_HeroType":2,"f_HeroCountry":1,"f_Attribute":"10015:800|10013:200","f_TokenID":0,"f_knowledge":"21-70","f_iconid":51,"f_info":""},"31":{"f_id":31,"f_HeroID":31,"f_name":"蔡文姬","f_Region":7,"f_HeroQuality":5,"f_HeroType":2,"f_HeroCountry":1,"f_Attribute":"10012:600|10016:400","f_TokenID":0,"f_knowledge":"21-70","f_iconid":54,"f_info":""},"32":{"f_id":32,"f_HeroID":32,"f_name":"吴国太","f_Region":2,"f_HeroQuality":4,"f_HeroType":2,"f_HeroCountry":1,"f_Attribute":"10013:600","f_TokenID":0,"f_knowledge":"21-50","f_iconid":59,"f_info":""},"33":{"f_id":33,"f_HeroID":33,"f_name":"祝融","f_Region":1,"f_HeroQuality":4,"f_HeroType":2,"f_HeroCountry":1,"f_Attribute":"10017:400|10012:200","f_TokenID":0,"f_knowledge":"21-50","f_iconid":22,"f_info":""},"34":{"f_id":34,"f_HeroID":34,"f_name":"张宁","f_Region":7,"f_HeroQuality":4,"f_HeroType":2,"f_HeroCountry":1,"f_Attribute":"10013:300|10014:300","f_TokenID":0,"f_knowledge":"21-50","f_iconid":2,"f_info":""},"35":{"f_id":35,"f_HeroID":35,"f_name":"黄月英","f_Region":4,"f_HeroQuality":4,"f_HeroType":2,"f_HeroCountry":1,"f_Attribute":"10012:300|10017:300","f_TokenID":0,"f_knowledge":"21-50","f_iconid":49,"f_info":""},"36":{"f_id":36,"f_HeroID":36,"f_name":"王元姬","f_Region":6,"f_HeroQuality":3,"f_HeroType":2,"f_HeroCountry":1,"f_Attribute":"10012:400","f_TokenID":0,"f_knowledge":"21-20","f_iconid":1,"f_info":""},"37":{"f_id":37,"f_HeroID":37,"f_name":"吕玲绮","f_Region":6,"f_HeroQuality":3,"f_HeroType":2,"f_HeroCountry":1,"f_Attribute":"10013:200|10014:200","f_TokenID":0,"f_knowledge":"21-20","f_iconid":56,"f_info":""},"38":{"f_id":38,"f_HeroID":38,"f_name":"马云禄","f_Region":7,"f_HeroQuality":3,"f_HeroType":2,"f_HeroCountry":1,"f_Attribute":"10016:300|10017:100","f_TokenID":0,"f_knowledge":"21-20","f_iconid":53,"f_info":""},"39":{"f_id":39,"f_HeroID":39,"f_name":"张春华","f_Region":5,"f_HeroQuality":3,"f_HeroType":2,"f_HeroCountry":1,"f_Attribute":"10013:300|10017:100","f_TokenID":0,"f_knowledge":"21-20","f_iconid":50,"f_info":""},"40":{"f_id":40,"f_HeroID":40,"f_name":"诸葛果","f_Region":1,"f_HeroQuality":3,"f_HeroType":2,"f_HeroCountry":1,"f_Attribute":"10014:400","f_TokenID":0,"f_knowledge":"21-20","f_iconid":48,"f_info":""},"41":{"f_id":41,"f_HeroID":41,"f_name":"孙尚香","f_Region":2,"f_HeroQuality":3,"f_HeroType":2,"f_HeroCountry":1,"f_Attribute":"10015:200|10012:200","f_TokenID":0,"f_knowledge":"21-20","f_iconid":3,"f_info":""},"42":{"f_id":42,"f_HeroID":42,"f_name":"关银屏","f_Region":4,"f_HeroQuality":2,"f_HeroType":2,"f_HeroCountry":1,"f_Attribute":"10013:200","f_TokenID":0,"f_knowledge":"21-10","f_iconid":55,"f_info":""},"43":{"f_id":43,"f_HeroID":43,"f_name":"步练师","f_Region":3,"f_HeroQuality":2,"f_HeroType":2,"f_HeroCountry":1,"f_Attribute":"10017:200","f_TokenID":0,"f_knowledge":"21-10","f_iconid":47,"f_info":""},"44":{"f_id":44,"f_HeroID":44,"f_name":"大乔","f_Region":2,"f_HeroQuality":2,"f_HeroType":2,"f_HeroCountry":1,"f_Attribute":"10014:200","f_TokenID":0,"f_knowledge":"21-10","f_iconid":46,"f_info":""},"45":{"f_id":45,"f_HeroID":45,"f_name":"小乔","f_Region":2,"f_HeroQuality":2,"f_HeroType":2,"f_HeroCountry":1,"f_Attribute":"10010:200","f_TokenID":0,"f_knowledge":"21-10","f_iconid":58,"f_info":""},"46":{"f_id":46,"f_HeroID":46,"f_name":"张星彩","f_Region":4,"f_HeroQuality":2,"f_HeroType":2,"f_HeroCountry":1,"f_Attribute":"10016:200","f_TokenID":0,"f_knowledge":"21-10","f_iconid":45,"f_info":""},"47":{"f_id":47,"f_HeroID":47,"f_name":"孙权","f_Region":2,"f_HeroQuality":6,"f_HeroType":3,"f_HeroCountry":1,"f_Attribute":"10027:1200|10003:12000","f_TokenID":46,"f_knowledge":"21-90","f_iconid":95,"f_info":""},"48":{"f_id":48,"f_HeroID":48,"f_name":"刘备","f_Region":1,"f_HeroQuality":6,"f_HeroType":3,"f_HeroCountry":1,"f_Attribute":"10028:1200|10004:3200","f_TokenID":48,"f_knowledge":"21-90","f_iconid":26,"f_info":""},"49":{"f_id":49,"f_HeroID":49,"f_name":"曹操","f_Region":3,"f_HeroQuality":6,"f_HeroType":3,"f_HeroCountry":1,"f_Attribute":"10029:1200|10005:1200","f_TokenID":43,"f_knowledge":"21-70","f_iconid":86,"f_info":""},"50":{"f_id":50,"f_HeroID":50,"f_name":"曹丕","f_Region":3,"f_HeroQuality":5,"f_HeroType":3,"f_HeroCountry":1,"f_Attribute":"10027:800|10003:8000","f_TokenID":0,"f_knowledge":"21-70","f_iconid":68,"f_info":""},"51":{"f_id":51,"f_HeroID":51,"f_name":"袁绍","f_Region":6,"f_HeroQuality":5,"f_HeroType":3,"f_HeroCountry":1,"f_Attribute":"10028:800|10003:8000","f_TokenID":0,"f_knowledge":"21-70","f_iconid":19,"f_info":""},"52":{"f_id":52,"f_HeroID":52,"f_name":"司马昭","f_Region":5,"f_HeroQuality":5,"f_HeroType":3,"f_HeroCountry":1,"f_Attribute":"10029:800|10005:800","f_TokenID":0,"f_knowledge":"21-70","f_iconid":31,"f_info":""},"53":{"f_id":53,"f_HeroID":53,"f_name":"孙坚","f_Region":2,"f_HeroQuality":5,"f_HeroType":3,"f_HeroCountry":1,"f_Attribute":"10028:600|10004:2500","f_TokenID":0,"f_knowledge":"21-70","f_iconid":88,"f_info":""},"54":{"f_id":54,"f_HeroID":54,"f_name":"袁术","f_Region":6,"f_HeroQuality":4,"f_HeroType":3,"f_HeroCountry":1,"f_Attribute":"10027:600|10004:2000","f_TokenID":0,"f_knowledge":"21-50","f_iconid":28,"f_info":""},"55":{"f_id":55,"f_HeroID":55,"f_name":"张角","f_Region":3,"f_HeroQuality":4,"f_HeroType":3,"f_HeroCountry":1,"f_Attribute":"10028:400|10003:6000","f_TokenID":0,"f_knowledge":"21-50","f_iconid":63,"f_info":""},"56":{"f_id":56,"f_HeroID":56,"f_name":"刘表","f_Region":4,"f_HeroQuality":4,"f_HeroType":3,"f_HeroCountry":1,"f_Attribute":"10029:600|10003:6000","f_TokenID":0,"f_knowledge":"21-50","f_iconid":66,"f_info":""},"57":{"f_id":57,"f_HeroID":57,"f_name":"董卓","f_Region":5,"f_HeroQuality":4,"f_HeroType":3,"f_HeroCountry":1,"f_Attribute":"10028:300|10003:9000","f_TokenID":0,"f_knowledge":"21-50","f_iconid":17,"f_info":""},"58":{"f_id":58,"f_HeroID":58,"f_name":"孟获","f_Region":1,"f_HeroQuality":4,"f_HeroType":3,"f_HeroCountry":1,"f_Attribute":"10027:500|10005:600","f_TokenID":0,"f_knowledge":"21-50","f_iconid":83,"f_info":""},"59":{"f_id":59,"f_HeroID":59,"f_name":"张鲁","f_Region":1,"f_HeroQuality":4,"f_HeroType":3,"f_HeroCountry":1,"f_Attribute":"10028:500|10005:600","f_TokenID":0,"f_knowledge":"21-50","f_iconid":20,"f_info":""},"60":{"f_id":60,"f_HeroID":60,"f_name":"马腾","f_Region":7,"f_HeroQuality":4,"f_HeroType":3,"f_HeroCountry":1,"f_Attribute":"10029:500|10004:2200","f_TokenID":0,"f_knowledge":"21-50","f_iconid":11,"f_info":""},"61":{"f_id":61,"f_HeroID":61,"f_name":"公孙瓒","f_Region":6,"f_HeroQuality":3,"f_HeroType":3,"f_HeroCountry":1,"f_Attribute":"10027:400|10003:5000","f_TokenID":0,"f_knowledge":"21-20","f_iconid":25,"f_info":""},"62":{"f_id":62,"f_HeroID":62,"f_name":"刘璋","f_Region":1,"f_HeroQuality":2,"f_HeroType":3,"f_HeroCountry":1,"f_Attribute":"10027:300|10004:1500","f_TokenID":0,"f_knowledge":"21-20","f_iconid":16,"f_info":""},"63":{"f_id":63,"f_HeroID":63,"f_name":"严白虎","f_Region":4,"f_HeroQuality":2,"f_HeroType":3,"f_HeroCountry":1,"f_Attribute":"10028:300|10005:500","f_TokenID":0,"f_knowledge":"21-20","f_iconid":29,"f_info":""},"64":{"f_id":64,"f_HeroID":64,"f_name":"张绣","f_Region":5,"f_HeroQuality":2,"f_HeroType":3,"f_HeroCountry":1,"f_Attribute":"10029:300|10003:4000","f_TokenID":0,"f_knowledge":"21-20","f_iconid":12,"f_info":""},"65":{"f_id":65,"f_HeroID":65,"f_name":"诸葛亮","f_Region":4,"f_HeroQuality":6,"f_HeroType":4,"f_HeroCountry":1,"f_Attribute":"10007:1000|10010:1000","f_TokenID":49,"f_knowledge":"21-90","f_iconid":72,"f_info":""},"66":{"f_id":66,"f_HeroID":66,"f_name":"周瑜","f_Region":2,"f_HeroQuality":6,"f_HeroType":4,"f_HeroCountry":1,"f_Attribute":"10006:1000|10009:1000","f_TokenID":49,"f_knowledge":"21-90","f_iconid":40,"f_info":""},"67":{"f_id":67,"f_HeroID":67,"f_name":"司马懿","f_Region":5,"f_HeroQuality":6,"f_HeroType":4,"f_HeroCountry":1,"f_Attribute":"10009:1000|10011:1000","f_TokenID":44,"f_knowledge":"21-90","f_iconid":73,"f_info":""},"68":{"f_id":68,"f_HeroID":68,"f_name":"郭嘉","f_Region":3,"f_HeroQuality":5,"f_HeroType":4,"f_HeroCountry":1,"f_Attribute":"10011:800|10007:700","f_TokenID":0,"f_knowledge":"21-70","f_iconid":61,"f_info":""},"69":{"f_id":69,"f_HeroID":69,"f_name":"钟会","f_Region":7,"f_HeroQuality":5,"f_HeroType":4,"f_HeroCountry":1,"f_Attribute":"10009:800|10006:700","f_TokenID":0,"f_knowledge":"21-70","f_iconid":10,"f_info":""},"70":{"f_id":70,"f_HeroID":70,"f_name":"陆逊","f_Region":2,"f_HeroQuality":4,"f_HeroType":4,"f_HeroCountry":1,"f_Attribute":"10008:600|10011:400","f_TokenID":0,"f_knowledge":"21-50","f_iconid":93,"f_info":""},"71":{"f_id":71,"f_HeroID":71,"f_name":"鲁肃","f_Region":2,"f_HeroQuality":4,"f_HeroType":4,"f_HeroCountry":1,"f_Attribute":"10010:600|10006:400","f_TokenID":0,"f_knowledge":"21-50","f_iconid":69,"f_info":""},"72":{"f_id":72,"f_HeroID":72,"f_name":"荀彧","f_Region":3,"f_HeroQuality":4,"f_HeroType":4,"f_HeroCountry":1,"f_Attribute":"10006:800|10010:200","f_TokenID":0,"f_knowledge":"21-50","f_iconid":67,"f_info":""},"73":{"f_id":73,"f_HeroID":73,"f_name":"庞统","f_Region":4,"f_HeroQuality":4,"f_HeroType":4,"f_HeroCountry":1,"f_Attribute":"10007:700|10008:300","f_TokenID":0,"f_knowledge":"21-50","f_iconid":74,"f_info":""},"74":{"f_id":74,"f_HeroID":74,"f_name":"贾诩","f_Region":5,"f_HeroQuality":4,"f_HeroType":4,"f_HeroCountry":1,"f_Attribute":"10006:300|10011:700","f_TokenID":0,"f_knowledge":"21-50","f_iconid":71,"f_info":""},"75":{"f_id":75,"f_HeroID":75,"f_name":"陈宫","f_Region":6,"f_HeroQuality":4,"f_HeroType":4,"f_HeroCountry":1,"f_Attribute":"10008:800|10010:200","f_TokenID":0,"f_knowledge":"21-50","f_iconid":70,"f_info":""},"76":{"f_id":76,"f_HeroID":76,"f_name":"吕蒙","f_Region":2,"f_HeroQuality":3,"f_HeroType":4,"f_HeroCountry":1,"f_Attribute":"10009:400|10007:100","f_TokenID":0,"f_knowledge":"21-20","f_iconid":32,"f_info":""},"77":{"f_id":77,"f_HeroID":77,"f_name":"程昱","f_Region":3,"f_HeroQuality":3,"f_HeroType":4,"f_HeroCountry":1,"f_Attribute":"10007:200|10008:300","f_TokenID":0,"f_knowledge":"21-20","f_iconid":62,"f_info":""},"78":{"f_id":78,"f_HeroID":78,"f_name":"李儒","f_Region":5,"f_HeroQuality":3,"f_HeroType":4,"f_HeroCountry":1,"f_Attribute":"10010:300|10008:200","f_TokenID":0,"f_knowledge":"21-20","f_iconid":99,"f_info":""},"79":{"f_id":79,"f_HeroID":79,"f_name":"沮授","f_Region":6,"f_HeroQuality":3,"f_HeroType":4,"f_HeroCountry":1,"f_Attribute":"10008:500","f_TokenID":0,"f_knowledge":"21-20","f_iconid":9,"f_info":""},"80":{"f_id":80,"f_HeroID":80,"f_name":"杨修","f_Region":7,"f_HeroQuality":3,"f_HeroType":4,"f_HeroCountry":1,"f_Attribute":"10010:500","f_TokenID":0,"f_knowledge":"21-20","f_iconid":76,"f_info":""},"81":{"f_id":81,"f_HeroID":81,"f_name":"刘烨","f_Region":7,"f_HeroQuality":3,"f_HeroType":4,"f_HeroCountry":1,"f_Attribute":"10007:400|10008:100","f_TokenID":0,"f_knowledge":"21-20","f_iconid":80,"f_info":""},"82":{"f_id":82,"f_HeroID":82,"f_name":"徐庶","f_Region":4,"f_HeroQuality":3,"f_HeroType":4,"f_HeroCountry":1,"f_Attribute":"10011:500","f_TokenID":0,"f_knowledge":"21-20","f_iconid":65,"f_info":""},"83":{"f_id":83,"f_HeroID":83,"f_name":"马良","f_Region":4,"f_HeroQuality":3,"f_HeroType":4,"f_HeroCountry":1,"f_Attribute":"10010:500","f_TokenID":0,"f_knowledge":"21-20","f_iconid":64,"f_info":""},"84":{"f_id":84,"f_HeroID":84,"f_name":"田丰","f_Region":6,"f_HeroQuality":2,"f_HeroType":4,"f_HeroCountry":1,"f_Attribute":"10008:300","f_TokenID":0,"f_knowledge":"21-10","f_iconid":8,"f_info":""},"85":{"f_id":85,"f_HeroID":85,"f_name":"满宠","f_Region":7,"f_HeroQuality":2,"f_HeroType":4,"f_HeroCountry":1,"f_Attribute":"10006:300","f_TokenID":0,"f_knowledge":"21-10","f_iconid":18,"f_info":""},"86":{"f_id":86,"f_HeroID":86,"f_name":"张松","f_Region":1,"f_HeroQuality":2,"f_HeroType":4,"f_HeroCountry":1,"f_Attribute":"10007:200|10006:100","f_TokenID":0,"f_knowledge":"21-10","f_iconid":90,"f_info":""},"87":{"f_id":87,"f_HeroID":87,"f_name":"法正","f_Region":1,"f_HeroQuality":2,"f_HeroType":4,"f_HeroCountry":1,"f_Attribute":"10009:300","f_TokenID":0,"f_knowledge":"21-10","f_iconid":43,"f_info":""},"88":{"f_id":88,"f_HeroID":88,"f_name":"文聘","f_Region":0,"f_HeroQuality":1,"f_HeroType":1,"f_HeroCountry":1,"f_Attribute":"10003:4500","f_TokenID":0,"f_knowledge":"21-5","f_iconid":37,"f_info":""},"89":{"f_id":89,"f_HeroID":89,"f_name":"高览","f_Region":0,"f_HeroQuality":1,"f_HeroType":1,"f_HeroCountry":1,"f_Attribute":"10004:1000","f_TokenID":0,"f_knowledge":"21-5","f_iconid":38,"f_info":""},"90":{"f_id":90,"f_HeroID":90,"f_name":"于禁","f_Region":0,"f_HeroQuality":1,"f_HeroType":1,"f_HeroCountry":1,"f_Attribute":"10005:300","f_TokenID":0,"f_knowledge":"21-5","f_iconid":77,"f_info":""},"91":{"f_id":91,"f_HeroID":91,"f_name":"丁奉","f_Region":0,"f_HeroQuality":1,"f_HeroType":1,"f_HeroCountry":1,"f_Attribute":"10002:200|10003:3000","f_TokenID":0,"f_knowledge":"21-5","f_iconid":79,"f_info":""},"92":{"f_id":92,"f_HeroID":92,"f_name":"周泰","f_Region":0,"f_HeroQuality":1,"f_HeroType":1,"f_HeroCountry":1,"f_Attribute":"10003:4000|10005:300","f_TokenID":0,"f_knowledge":"21-5","f_iconid":35,"f_info":""},"93":{"f_id":93,"f_HeroID":93,"f_name":"乐进","f_Region":0,"f_HeroQuality":1,"f_HeroType":1,"f_HeroCountry":1,"f_Attribute":"10004:700|10002:200","f_TokenID":0,"f_knowledge":"21-5","f_iconid":30,"f_info":""},"94":{"f_id":94,"f_HeroID":94,"f_name":"木鹿大王","f_Region":0,"f_HeroQuality":1,"f_HeroType":3,"f_HeroCountry":1,"f_Attribute":"10014:100","f_TokenID":0,"f_knowledge":"21-5","f_iconid":5,"f_info":""},"95":{"f_id":95,"f_HeroID":95,"f_name":"朵思大王","f_Region":0,"f_HeroQuality":1,"f_HeroType":3,"f_HeroCountry":1,"f_Attribute":"10013:100","f_TokenID":0,"f_knowledge":"21-5","f_iconid":39,"f_info":""},"96":{"f_id":96,"f_HeroID":96,"f_name":"孙鲁班","f_Region":0,"f_HeroQuality":1,"f_HeroType":2,"f_HeroCountry":1,"f_Attribute":"10028:500|10005:200","f_TokenID":0,"f_knowledge":"21-5","f_iconid":91,"f_info":""},"97":{"f_id":97,"f_HeroID":97,"f_name":"孙鲁育","f_Region":0,"f_HeroQuality":1,"f_HeroType":2,"f_HeroCountry":1,"f_Attribute":"10029:200|10003:3000","f_TokenID":0,"f_knowledge":"21-5","f_iconid":92,"f_info":""},"98":{"f_id":98,"f_HeroID":98,"f_name":"马谡","f_Region":0,"f_HeroQuality":1,"f_HeroType":4,"f_HeroCountry":1,"f_Attribute":"10017:200","f_TokenID":0,"f_knowledge":"21-5","f_iconid":34,"f_info":""},"99":{"f_id":99,"f_HeroID":99,"f_name":"荀攸","f_Region":0,"f_HeroQuality":1,"f_HeroType":4,"f_HeroCountry":1,"f_Attribute":"10010:200","f_TokenID":0,"f_knowledge":"21-5","f_iconid":87,"f_info":""},"100":{"f_id":100,"f_HeroID":100,"f_name":"益州残页上","f_Region":1,"f_HeroQuality":7,"f_HeroType":0,"f_HeroCountry":0,"f_Attribute":"","f_TokenID":0,"f_knowledge":"","f_iconid":108,"f_info":"看来你就是老夫等的有缘人，这本《益州残页上》就送给你了"},"101":{"f_id":101,"f_HeroID":101,"f_name":"益州残页中","f_Region":1,"f_HeroQuality":7,"f_HeroType":0,"f_HeroCountry":0,"f_Attribute":"","f_TokenID":0,"f_knowledge":"","f_iconid":108,"f_info":"看来你就是老夫等的有缘人，这本《益州残页中》就送给你了"},"102":{"f_id":102,"f_HeroID":102,"f_name":"益州残页下","f_Region":1,"f_HeroQuality":7,"f_HeroType":0,"f_HeroCountry":0,"f_Attribute":"","f_TokenID":0,"f_knowledge":"","f_iconid":108,"f_info":"看来你就是老夫等的有缘人，这本《益州残页下》就送给你了"},"103":{"f_id":103,"f_HeroID":103,"f_name":"扬州残页上","f_Region":2,"f_HeroQuality":7,"f_HeroType":0,"f_HeroCountry":0,"f_Attribute":"","f_TokenID":0,"f_knowledge":"","f_iconid":108,"f_info":"看来你就是老夫等的有缘人，这本《扬州残页上》就送给你了"},"104":{"f_id":104,"f_HeroID":104,"f_name":"扬州残页中","f_Region":2,"f_HeroQuality":7,"f_HeroType":0,"f_HeroCountry":0,"f_Attribute":"","f_TokenID":0,"f_knowledge":"","f_iconid":108,"f_info":"看来你就是老夫等的有缘人，这本《扬州残页中》就送给你了"},"105":{"f_id":105,"f_HeroID":105,"f_name":"扬州残页下","f_Region":2,"f_HeroQuality":7,"f_HeroType":0,"f_HeroCountry":0,"f_Attribute":"","f_TokenID":0,"f_knowledge":"","f_iconid":108,"f_info":"看来你就是老夫等的有缘人，这本《扬州残页下》就送给你了"},"106":{"f_id":106,"f_HeroID":106,"f_name":"兖州残页上","f_Region":3,"f_HeroQuality":7,"f_HeroType":0,"f_HeroCountry":0,"f_Attribute":"","f_TokenID":0,"f_knowledge":"","f_iconid":108,"f_info":"看来你就是老夫等的有缘人，这本《兖州残页上》就送给你了"},"107":{"f_id":107,"f_HeroID":107,"f_name":"兖州残页中","f_Region":3,"f_HeroQuality":7,"f_HeroType":0,"f_HeroCountry":0,"f_Attribute":"","f_TokenID":0,"f_knowledge":"","f_iconid":108,"f_info":"看来你就是老夫等的有缘人，这本《兖州残页中》就送给你了"},"108":{"f_id":108,"f_HeroID":108,"f_name":"兖州残页下","f_Region":3,"f_HeroQuality":7,"f_HeroType":0,"f_HeroCountry":0,"f_Attribute":"","f_TokenID":0,"f_knowledge":"","f_iconid":108,"f_info":"看来你就是老夫等的有缘人，这本《兖州残页下》就送给你了"},"109":{"f_id":109,"f_HeroID":109,"f_name":"荆州残页上","f_Region":4,"f_HeroQuality":7,"f_HeroType":0,"f_HeroCountry":0,"f_Attribute":"","f_TokenID":0,"f_knowledge":"","f_iconid":108,"f_info":"看来你就是老夫等的有缘人，这本《荆州残页上》就送给你了"},"110":{"f_id":110,"f_HeroID":110,"f_name":"荆州残页中","f_Region":4,"f_HeroQuality":7,"f_HeroType":0,"f_HeroCountry":0,"f_Attribute":"","f_TokenID":0,"f_knowledge":"","f_iconid":108,"f_info":"看来你就是老夫等的有缘人，这本《荆州残页中》就送给你了"},"111":{"f_id":111,"f_HeroID":111,"f_name":"荆州残页下","f_Region":4,"f_HeroQuality":7,"f_HeroType":0,"f_HeroCountry":0,"f_Attribute":"","f_TokenID":0,"f_knowledge":"","f_iconid":108,"f_info":"看来你就是老夫等的有缘人，这本《荆州残页下》就送给你了"},"112":{"f_id":112,"f_HeroID":112,"f_name":"雍州残页上","f_Region":5,"f_HeroQuality":7,"f_HeroType":0,"f_HeroCountry":0,"f_Attribute":"","f_TokenID":0,"f_knowledge":"","f_iconid":108,"f_info":"看来你就是老夫等的有缘人，这本《雍州残页上》就送给你了"},"113":{"f_id":113,"f_HeroID":113,"f_name":"雍州残页中","f_Region":5,"f_HeroQuality":7,"f_HeroType":0,"f_HeroCountry":0,"f_Attribute":"","f_TokenID":0,"f_knowledge":"","f_iconid":108,"f_info":"看来你就是老夫等的有缘人，这本《雍州残页中》就送给你了"},"114":{"f_id":114,"f_HeroID":114,"f_name":"雍州残页下","f_Region":5,"f_HeroQuality":7,"f_HeroType":0,"f_HeroCountry":0,"f_Attribute":"","f_TokenID":0,"f_knowledge":"","f_iconid":108,"f_info":"看来你就是老夫等的有缘人，这本《雍州残页下》就送给你了"},"115":{"f_id":115,"f_HeroID":115,"f_name":"冀州残页上","f_Region":6,"f_HeroQuality":7,"f_HeroType":0,"f_HeroCountry":0,"f_Attribute":"","f_TokenID":0,"f_knowledge":"","f_iconid":108,"f_info":"看来你就是老夫等的有缘人，这本《冀州残页上》就送给你了"},"116":{"f_id":116,"f_HeroID":116,"f_name":"冀州残页中","f_Region":6,"f_HeroQuality":7,"f_HeroType":0,"f_HeroCountry":0,"f_Attribute":"","f_TokenID":0,"f_knowledge":"","f_iconid":108,"f_info":"看来你就是老夫等的有缘人，这本《冀州残页中》就送给你了"},"117":{"f_id":117,"f_HeroID":117,"f_name":"冀州残页下","f_Region":6,"f_HeroQuality":7,"f_HeroType":0,"f_HeroCountry":0,"f_Attribute":"","f_TokenID":0,"f_knowledge":"","f_iconid":108,"f_info":"看来你就是老夫等的有缘人，这本《冀州残页下》就送给你了"},"118":{"f_id":118,"f_HeroID":118,"f_name":"凉州残页上","f_Region":7,"f_HeroQuality":7,"f_HeroType":0,"f_HeroCountry":0,"f_Attribute":"","f_TokenID":0,"f_knowledge":"","f_iconid":108,"f_info":"看来你就是老夫等的有缘人，这本《凉州残页上》就送给你了"},"119":{"f_id":119,"f_HeroID":119,"f_name":"凉州残页中","f_Region":7,"f_HeroQuality":7,"f_HeroType":0,"f_HeroCountry":0,"f_Attribute":"","f_TokenID":0,"f_knowledge":"","f_iconid":108,"f_info":"看来你就是老夫等的有缘人，这本《凉州残页中》就送给你了"},"120":{"f_id":120,"f_HeroID":120,"f_name":"凉州残页下","f_Region":7,"f_HeroQuality":7,"f_HeroType":0,"f_HeroCountry":0,"f_Attribute":"","f_TokenID":0,"f_knowledge":"","f_iconid":108,"f_info":"看来你就是老夫等的有缘人，这本《凉州残页下》就送给你了"},"123":{"f_id":123,"f_HeroID":123,"f_name":"乞丐","f_Region":0,"f_HeroQuality":7,"f_HeroType":0,"f_HeroCountry":0,"f_Attribute":"","f_TokenID":0,"f_knowledge":"","f_iconid":106,"f_info":"贫穷的乞丐只是路过还在你这踢伤了脚，好在他并没有敲诈你"},"124":{"f_id":124,"f_HeroID":124,"f_name":"富商","f_Region":0,"f_HeroQuality":7,"f_HeroType":0,"f_HeroCountry":0,"f_Attribute":"","f_TokenID":0,"f_knowledge":"","f_iconid":107,"f_info":"慷慨的富商非常感谢你的招待，并赠送了你一些小费"},"125":{"f_id":125,"f_HeroID":125,"f_name":"文鸳","f_Region":8,"f_HeroQuality":6,"f_HeroType":1,"f_HeroCountry":0,"f_Attribute":"10004:3800|10002:750","f_TokenID":40,"f_knowledge":"21-90","f_iconid":147,"f_info":""},"126":{"f_id":126,"f_HeroID":126,"f_name":"魏延","f_Region":8,"f_HeroQuality":5,"f_HeroType":1,"f_HeroCountry":0,"f_Attribute":"10003:13000|10005:1000","f_TokenID":0,"f_knowledge":"21-70","f_iconid":148,"f_info":""},"127":{"f_id":127,"f_HeroID":127,"f_name":"管辂","f_Region":8,"f_HeroQuality":5,"f_HeroType":4,"f_HeroCountry":0,"f_Attribute":"10011:900|10008:900","f_TokenID":0,"f_knowledge":"21-70","f_iconid":149,"f_info":""},"128":{"f_id":128,"f_HeroID":128,"f_name":"华佗","f_Region":8,"f_HeroQuality":5,"f_HeroType":4,"f_HeroCountry":0,"f_Attribute":"10021:900|10006:750","f_TokenID":0,"f_knowledge":"21-70","f_iconid":150,"f_info":""},"129":{"f_id":129,"f_HeroID":129,"f_name":"南华老仙","f_Region":8,"f_HeroQuality":5,"f_HeroType":3,"f_HeroCountry":0,"f_Attribute":"10027:1000|10004:2800","f_TokenID":0,"f_knowledge":"21-70","f_iconid":151,"f_info":""},"130":{"f_id":130,"f_HeroID":130,"f_name":"紫虚上人","f_Region":8,"f_HeroQuality":5,"f_HeroType":3,"f_HeroCountry":0,"f_Attribute":"10028:1000|10003:9900","f_TokenID":0,"f_knowledge":"21-70","f_iconid":152,"f_info":""},"131":{"f_id":131,"f_HeroID":131,"f_name":"张宝","f_Region":8,"f_HeroQuality":4,"f_HeroType":1,"f_HeroCountry":0,"f_Attribute":"10002:380|10003:7500","f_TokenID":0,"f_knowledge":"21-50","f_iconid":153,"f_info":""},"132":{"f_id":132,"f_HeroID":132,"f_name":"曹节","f_Region":8,"f_HeroQuality":4,"f_HeroType":2,"f_HeroCountry":0,"f_Attribute":"10015:700","f_TokenID":0,"f_knowledge":"21-50","f_iconid":154,"f_info":""},"133":{"f_id":133,"f_HeroID":133,"f_name":"李严","f_Region":8,"f_HeroQuality":4,"f_HeroType":3,"f_HeroCountry":0,"f_Attribute":"10007:700|10010:400","f_TokenID":0,"f_knowledge":"21-50","f_iconid":155,"f_info":""},"134":{"f_id":134,"f_HeroID":134,"f_name":"轲比能","f_Region":8,"f_HeroQuality":4,"f_HeroType":4,"f_HeroCountry":0,"f_Attribute":"10029:700|10004:2050","f_TokenID":0,"f_knowledge":"21-50","f_iconid":156,"f_info":""},"135":{"f_id":135,"f_HeroID":135,"f_name":"文钦","f_Region":8,"f_HeroQuality":3,"f_HeroType":1,"f_HeroCountry":0,"f_Attribute":"10004:2100|10005:750","f_TokenID":0,"f_knowledge":"21-20","f_iconid":157,"f_info":""},"136":{"f_id":136,"f_HeroID":136,"f_name":"糜夫人","f_Region":8,"f_HeroQuality":3,"f_HeroType":2,"f_HeroCountry":0,"f_Attribute":"10013:200|10016:350","f_TokenID":0,"f_knowledge":"21-20","f_iconid":158,"f_info":""},"137":{"f_id":137,"f_HeroID":137,"f_name":"许攸","f_Region":8,"f_HeroQuality":3,"f_HeroType":3,"f_HeroCountry":0,"f_Attribute":"10009:600","f_TokenID":0,"f_knowledge":"21-20","f_iconid":159,"f_info":""},"138":{"f_id":138,"f_HeroID":138,"f_name":"刘协","f_Region":8,"f_HeroQuality":3,"f_HeroType":4,"f_HeroCountry":0,"f_Attribute":"10027:500|10004:1550","f_TokenID":0,"f_knowledge":"21-20","f_iconid":160,"f_info":""},"139":{"f_id":139,"f_HeroID":139,"f_name":"张梁","f_Region":8,"f_HeroQuality":2,"f_HeroType":1,"f_HeroCountry":0,"f_Attribute":"10003:5650|10004:1600","f_TokenID":0,"f_knowledge":"21-10","f_iconid":161,"f_info":""},"140":{"f_id":140,"f_HeroID":140,"f_name":"夏侯涓","f_Region":8,"f_HeroQuality":2,"f_HeroType":2,"f_HeroCountry":0,"f_Attribute":"10012:250","f_TokenID":0,"f_knowledge":"21-10","f_iconid":162,"f_info":""},"141":{"f_id":141,"f_HeroID":141,"f_name":"审配","f_Region":8,"f_HeroQuality":2,"f_HeroType":3,"f_HeroCountry":0,"f_Attribute":"10010:400","f_TokenID":0,"f_knowledge":"21-10","f_iconid":163,"f_info":""},"142":{"f_id":142,"f_HeroID":142,"f_name":"带来洞主","f_Region":8,"f_HeroQuality":2,"f_HeroType":4,"f_HeroCountry":0,"f_Attribute":"10028:250|10003:7000","f_TokenID":0,"f_knowledge":"21-10","f_iconid":164,"f_info":""},"143":{"f_id":143,"f_HeroID":143,"f_name":"关平","f_Region":1,"f_HeroQuality":4,"f_HeroType":1,"f_HeroCountry":0,"f_Attribute":"10005:660|10004:2220","f_TokenID":0,"f_knowledge":"21-50","f_iconid":109,"f_info":""},"144":{"f_id":144,"f_HeroID":144,"f_name":"韩当","f_Region":4,"f_HeroQuality":3,"f_HeroType":1,"f_HeroCountry":0,"f_Attribute":"10002:280|10005:820","f_TokenID":0,"f_knowledge":"21-20","f_iconid":110,"f_info":""},"145":{"f_id":145,"f_HeroID":145,"f_name":"周仓","f_Region":1,"f_HeroQuality":2,"f_HeroType":1,"f_HeroCountry":0,"f_Attribute":"10004:1600|10005:550","f_TokenID":0,"f_knowledge":"21-10","f_iconid":111,"f_info":""},"146":{"f_id":146,"f_HeroID":146,"f_name":"邓艾","f_Region":2,"f_HeroQuality":4,"f_HeroType":1,"f_HeroCountry":0,"f_Attribute":"10003:7800|10004:2200","f_TokenID":0,"f_knowledge":"21-50","f_iconid":112,"f_info":""},"147":{"f_id":147,"f_HeroID":147,"f_name":"诸葛瞻","f_Region":4,"f_HeroQuality":2,"f_HeroType":1,"f_HeroCountry":0,"f_Attribute":"10003:5700|10005:1550","f_TokenID":0,"f_knowledge":"21-10","f_iconid":113,"f_info":""},"148":{"f_id":148,"f_HeroID":148,"f_name":"曹休","f_Region":5,"f_HeroQuality":2,"f_HeroType":1,"f_HeroCountry":0,"f_Attribute":"10005:550|10004:2400","f_TokenID":0,"f_knowledge":"21-10","f_iconid":114,"f_info":""},"149":{"f_id":149,"f_HeroID":149,"f_name":"张苞","f_Region":6,"f_HeroQuality":3,"f_HeroType":1,"f_HeroCountry":0,"f_Attribute":"10002:315|10003:5700","f_TokenID":0,"f_knowledge":"21-20","f_iconid":115,"f_info":""},"150":{"f_id":150,"f_HeroID":150,"f_name":"高顺","f_Region":3,"f_HeroQuality":4,"f_HeroType":1,"f_HeroCountry":0,"f_Attribute":"10003:7800|10005:720","f_TokenID":0,"f_knowledge":"21-50","f_iconid":116,"f_info":""},"151":{"f_id":151,"f_HeroID":151,"f_name":"程普","f_Region":7,"f_HeroQuality":3,"f_HeroType":1,"f_HeroCountry":0,"f_Attribute":"10004:1990|10003:6770","f_TokenID":0,"f_knowledge":"21-20","f_iconid":117,"f_info":""},"152":{"f_id":152,"f_HeroID":152,"f_name":"徐盛","f_Region":4,"f_HeroQuality":4,"f_HeroType":1,"f_HeroCountry":0,"f_Attribute":"10004:2450|10005:600","f_TokenID":0,"f_knowledge":"21-50","f_iconid":118,"f_info":""},"153":{"f_id":153,"f_HeroID":153,"f_name":"祖茂","f_Region":6,"f_HeroQuality":2,"f_HeroType":1,"f_HeroCountry":0,"f_Attribute":"10002:400","f_TokenID":0,"f_knowledge":"21-10","f_iconid":119,"f_info":""},"154":{"f_id":154,"f_HeroID":154,"f_name":"潘凤","f_Region":5,"f_HeroQuality":4,"f_HeroType":1,"f_HeroCountry":0,"f_Attribute":"10004:3000","f_TokenID":0,"f_knowledge":"21-50","f_iconid":120,"f_info":""},"155":{"f_id":155,"f_HeroID":155,"f_name":"吴苋","f_Region":1,"f_HeroQuality":2,"f_HeroType":2,"f_HeroCountry":0,"f_Attribute":"10013:250","f_TokenID":0,"f_knowledge":"21-10","f_iconid":121,"f_info":""},"156":{"f_id":156,"f_HeroID":156,"f_name":"蔡夫人","f_Region":5,"f_HeroQuality":2,"f_HeroType":2,"f_HeroCountry":0,"f_Attribute":"10014:250","f_TokenID":0,"f_knowledge":"21-10","f_iconid":122,"f_info":""},"157":{"f_id":157,"f_HeroID":157,"f_name":"夏侯氏","f_Region":3,"f_HeroQuality":4,"f_HeroType":2,"f_HeroCountry":0,"f_Attribute":"10016:400|10014:450","f_TokenID":0,"f_knowledge":"21-50","f_iconid":123,"f_info":""},"158":{"f_id":158,"f_HeroID":158,"f_name":"李婉","f_Region":6,"f_HeroQuality":2,"f_HeroType":2,"f_HeroCountry":0,"f_Attribute":"10015:250","f_TokenID":0,"f_knowledge":"21-10","f_iconid":124,"f_info":""},"159":{"f_id":159,"f_HeroID":159,"f_name":"鲍三娘","f_Region":5,"f_HeroQuality":4,"f_HeroType":2,"f_HeroCountry":0,"f_Attribute":"10013:350|10015:400","f_TokenID":0,"f_knowledge":"21-50","f_iconid":125,"f_info":""},"160":{"f_id":160,"f_HeroID":160,"f_name":"郭皇后","f_Region":7,"f_HeroQuality":2,"f_HeroType":2,"f_HeroCountry":0,"f_Attribute":"10016:250","f_TokenID":0,"f_knowledge":"21-10","f_iconid":126,"f_info":""},"161":{"f_id":161,"f_HeroID":161,"f_name":"辛宪英","f_Region":3,"f_HeroQuality":3,"f_HeroType":2,"f_HeroCountry":0,"f_Attribute":"10017:450","f_TokenID":0,"f_knowledge":"21-20","f_iconid":127,"f_info":""},"162":{"f_id":162,"f_HeroID":162,"f_name":"金乡公主","f_Region":4,"f_HeroQuality":3,"f_HeroType":2,"f_HeroCountry":0,"f_Attribute":"10017:400|10014:150","f_TokenID":0,"f_knowledge":"21-20","f_iconid":128,"f_info":""},"163":{"f_id":163,"f_HeroID":163,"f_name":"王异","f_Region":6,"f_HeroQuality":4,"f_HeroType":2,"f_HeroCountry":0,"f_Attribute":"10015:350|10012:450","f_TokenID":0,"f_knowledge":"21-50","f_iconid":129,"f_info":""},"164":{"f_id":164,"f_HeroID":164,"f_name":"陶谦","f_Region":1,"f_HeroQuality":3,"f_HeroType":3,"f_HeroCountry":0,"f_Attribute":"10029:500|10003:6500","f_TokenID":0,"f_knowledge":"21-20","f_iconid":130,"f_info":""},"165":{"f_id":165,"f_HeroID":165,"f_name":"士燮","f_Region":2,"f_HeroQuality":3,"f_HeroType":3,"f_HeroCountry":0,"f_Attribute":"10027:400|10004:1900","f_TokenID":0,"f_knowledge":"21-20","f_iconid":131,"f_info":""},"166":{"f_id":166,"f_HeroID":166,"f_name":"公孙度","f_Region":2,"f_HeroQuality":2,"f_HeroType":3,"f_HeroCountry":0,"f_Attribute":"10028:450|10005:500","f_TokenID":0,"f_knowledge":"21-10","f_iconid":132,"f_info":""},"167":{"f_id":167,"f_HeroID":167,"f_name":"张杨","f_Region":3,"f_HeroQuality":2,"f_HeroType":3,"f_HeroCountry":0,"f_Attribute":"10029:400|10005:550","f_TokenID":0,"f_knowledge":"21-10","f_iconid":133,"f_info":""},"168":{"f_id":168,"f_HeroID":168,"f_name":"刘虞","f_Region":6,"f_HeroQuality":2,"f_HeroType":3,"f_HeroCountry":0,"f_Attribute":"10027:400|10004:1600","f_TokenID":0,"f_knowledge":"21-10","f_iconid":134,"f_info":""},"169":{"f_id":169,"f_HeroID":169,"f_name":"孔融","f_Region":3,"f_HeroQuality":3,"f_HeroType":3,"f_HeroCountry":0,"f_Attribute":"10028:500|10004:1850","f_TokenID":0,"f_knowledge":"21-20","f_iconid":135,"f_info":""},"170":{"f_id":170,"f_HeroID":170,"f_name":"丁原","f_Region":2,"f_HeroQuality":4,"f_HeroType":3,"f_HeroCountry":0,"f_Attribute":"10029:700|10005:850","f_TokenID":0,"f_knowledge":"21-50","f_iconid":136,"f_info":""},"171":{"f_id":171,"f_HeroID":171,"f_name":"韩馥","f_Region":4,"f_HeroQuality":3,"f_HeroType":3,"f_HeroCountry":0,"f_Attribute":"10027:500|10005:550","f_TokenID":0,"f_knowledge":"21-20","f_iconid":137,"f_info":""},"172":{"f_id":172,"f_HeroID":172,"f_name":"刘岱","f_Region":5,"f_HeroQuality":3,"f_HeroType":3,"f_HeroCountry":0,"f_Attribute":"10028:500|10003:6000","f_TokenID":0,"f_knowledge":"21-20","f_iconid":138,"f_info":""},"173":{"f_id":173,"f_HeroID":173,"f_name":"乔瑁","f_Region":7,"f_HeroQuality":3,"f_HeroType":3,"f_HeroCountry":0,"f_Attribute":"10029:500|10005:700","f_TokenID":0,"f_knowledge":"21-20","f_iconid":139,"f_info":""},"174":{"f_id":174,"f_HeroID":174,"f_name":"袁遗","f_Region":7,"f_HeroQuality":2,"f_HeroType":3,"f_HeroCountry":0,"f_Attribute":"10027:400|10004:1650","f_TokenID":0,"f_knowledge":"21-10","f_iconid":140,"f_info":""},"175":{"f_id":175,"f_HeroID":175,"f_name":"董允","f_Region":5,"f_HeroQuality":2,"f_HeroType":4,"f_HeroCountry":0,"f_Attribute":"10009:100|10007:300","f_TokenID":0,"f_knowledge":"21-10","f_iconid":141,"f_info":""},"176":{"f_id":176,"f_HeroID":176,"f_name":"张昭","f_Region":3,"f_HeroQuality":2,"f_HeroType":4,"f_HeroCountry":0,"f_Attribute":"10006:300|10009:100","f_TokenID":0,"f_knowledge":"21-10","f_iconid":142,"f_info":""},"177":{"f_id":177,"f_HeroID":177,"f_name":"张纮","f_Region":4,"f_HeroQuality":2,"f_HeroType":4,"f_HeroCountry":0,"f_Attribute":"10007:200|10005:200","f_TokenID":0,"f_knowledge":"21-10","f_iconid":143,"f_info":""},"178":{"f_id":178,"f_HeroID":178,"f_name":"陈群","f_Region":2,"f_HeroQuality":2,"f_HeroType":4,"f_HeroCountry":0,"f_Attribute":"10010:300|10010:100","f_TokenID":0,"f_knowledge":"21-10","f_iconid":144,"f_info":""},"179":{"f_id":179,"f_HeroID":179,"f_name":"曹植","f_Region":1,"f_HeroQuality":3,"f_HeroType":4,"f_HeroCountry":0,"f_Attribute":"10011:600","f_TokenID":0,"f_knowledge":"21-20","f_iconid":145,"f_info":""},"180":{"f_id":180,"f_HeroID":180,"f_name":"荀攸(魏)","f_Region":1,"f_HeroQuality":4,"f_HeroType":4,"f_HeroCountry":0,"f_Attribute":"10008:800|10010:350","f_TokenID":0,"f_knowledge":"21-50","f_iconid":146,"f_info":""},"181":{"f_id":181,"f_HeroID":181,"f_name":"刘晔","f_Region":7,"f_HeroQuality":4,"f_HeroType":4,"f_HeroCountry":0,"f_Attribute":"10009:800|10006:350","f_TokenID":0,"f_knowledge":"21-50","f_iconid":165,"f_info":""},"182":{"f_id":182,"f_HeroID":182,"f_name":"青州残页上","f_Region":8,"f_HeroQuality":7,"f_HeroType":0,"f_HeroCountry":0,"f_Attribute":"","f_TokenID":0,"f_knowledge":"","f_iconid":108,"f_info":"看来你就是老夫等的有缘人，这本《青州残页上》就送给你了"},"183":{"f_id":183,"f_HeroID":183,"f_name":"青州残页中","f_Region":8,"f_HeroQuality":7,"f_HeroType":0,"f_HeroCountry":0,"f_Attribute":"","f_TokenID":0,"f_knowledge":"","f_iconid":108,"f_info":"看来你就是老夫等的有缘人，这本《青州残页中》就送给你了"},"184":{"f_id":184,"f_HeroID":184,"f_name":"青州残页下","f_Region":8,"f_HeroQuality":7,"f_HeroType":0,"f_HeroCountry":0,"f_Attribute":"","f_TokenID":0,"f_knowledge":"","f_iconid":108,"f_info":"看来你就是老夫等的有缘人，这本《青州残页下》就送给你了"},"185":{"f_id":185,"f_HeroID":185,"f_name":"葛玄","f_Region":0,"f_HeroQuality":6,"f_HeroType":1,"f_HeroCountry":0,"f_Attribute":"10007:1400|10008:1000","f_TokenID":0,"f_knowledge":"21-90","f_desc":"","f_iconid":166,"f_info":""}}}