{"mDataMap":{"1":{"f_id":1,"f_SeverType":"1;2;9","f_content":"dldTip2"},"2":{"f_id":2,"f_SeverType":"1;2;9","f_content":"dldTip3"},"3":{"f_id":3,"f_SeverType":"1;4;2;3;9","f_content":"dldTip4"},"4":{"f_id":4,"f_SeverType":"1;5;2;6;9","f_content":"dldTip5"},"5":{"f_id":5,"f_SeverType":"1;5;2;6;3;9","f_content":"dldTip6"},"6":{"f_id":6,"f_SeverType":"1;4;2;9","f_content":"dldTip7"},"7":{"f_id":7,"f_SeverType":"1;4;2;3;9","f_content":"dldTip8"},"8":{"f_id":8,"f_SeverType":"1;5;4;2;6;3;9","f_content":"dldTip9"},"9":{"f_id":9,"f_SeverType":"7;1;5;9","f_content":"dldTip10"},"10":{"f_id":10,"f_SeverType":"2","f_content":"dldTip11"},"11":{"f_id":11,"f_SeverType":"4;2;3","f_content":"dldTip12"}}}