{"type":"View","props":{"width":334,"height":407},"compId":2,"child":[{"type":"Image","props":{"y":0,"x":0,"width":334,"var":"bg","skin":"remote/main/main/db_3.png","sizeGrid":"18,22,19,20","height":407},"compId":4},{"type":"Label","props":{"y":114,"x":138,"width":159,"var":"nametf","text":"火之高兴","strokeColor":"#7C430C","stroke":3,"height":25,"fontSize":25,"font":"BOLD","color":"#FB5AFB","align":"left"},"compId":6},{"type":"Sprite","props":{"y":198,"x":40,"texture":"remote/main/main/lingxing.png"},"compId":7},{"type":"Sprite","props":{"y":274,"x":41,"texture":"remote/main/main/lingxing.png"},"compId":8},{"type":"Image","props":{"y":202,"x":44,"var":"kong2","skin":"remote/main/main/lingixng_1.png"},"compId":9},{"type":"Image","props":{"y":278,"x":45,"var":"kong4","skin":"remote/main/main/lingixng_1.png"},"compId":10},{"type":"Label","props":{"y":198,"x":80,"var":"tf5","text":"2件套","strokeColor":"#9F540C","stroke":3,"fontSize":25,"font":"BOLD","color":"#F9F0BB","align":"right"},"compId":11},{"type":"Label","props":{"y":276,"x":85,"var":"tf6","text":"4件套","strokeColor":"#9F540C","stroke":3,"fontSize":25,"font":"BOLD","color":"#F9F0BB","align":"right"},"compId":12},{"type":"ui_soul_tip_attr_item2","props":{"y":229,"x":80,"var":"cellAttr2","runtime":"ui.views.soul.ui_soul_tip_attr_item2UI"},"compId":13},{"type":"ui_soul_tip_attr_item2","props":{"y":308,"x":80,"var":"cellAttr4","runtime":"ui.views.soul.ui_soul_tip_attr_item2UI"},"compId":14},{"type":"Image","props":{"y":23,"x":66,"width":197,"var":"bg5","skin":"remote/common/base/sxk.png","sizeGrid":"0,25,0,23","height":43},"compId":15,"child":[{"type":"Label","props":{"var":"tf4","text":"套装属性","fontSize":25,"font":"BOLD","color":"#B1713C","centerY":0,"centerX":0},"compId":16}]},{"type":"Image","props":{"y":75.5,"x":37.25,"var":"bg11","skin":"remote/soul/zhk1.png","scaleY":1,"scaleX":1},"compId":19},{"type":"ui_soul_small_icon","props":{"y":65,"x":31,"var":"headPortrait","runtime":"ui.views.soul.ui_soul_small_iconUI"},"compId":18}],"loadList":["remote/main/main/db_3.png","remote/main/main/lingxing.png","remote/main/main/lingixng_1.png","views/soul/ui_soul_tip_attr_item2.scene","remote/common/base/sxk.png","remote/soul/zhk1.png","views/soul/ui_soul_small_icon.ui"],"loadList3D":[]}