{"mDataMap":{"1":{"f_id":1,"f_Days":1,"f_Item":"3-30|9-10|2-5000","f_RewardsType":0},"2":{"f_id":2,"f_Days":2,"f_Item":"407-1|9-10|19-6","f_RewardsType":0},"3":{"f_id":3,"f_Days":3,"f_Item":"1-350|1-350|335-6","f_RewardsType":0},"4":{"f_id":4,"f_Days":4,"f_Item":"8-3000|334-3000|336-3000","f_RewardsType":0},"5":{"f_id":5,"f_Days":5,"f_Item":"59-3|293-60|104-5000","f_RewardsType":0},"6":{"f_id":6,"f_Days":6,"f_Item":"11-3|12-10|2-10000","f_RewardsType":0},"7":{"f_id":7,"f_Days":7,"f_Item":"402-1|415-1|2-30000|1-500|20-50","f_RewardsType":0}}}