{"mDataMap":{"1":{"f_id":1,"f_exchangeRwards":"87-1","f_PreCost":"87-1","f_PreRewards":"88-10","f_MinRate":100,"f_Specialpara1":50,"f_exchangeCost1":"86-10","f_type":0,"f_mainicon":87,"f_shopicon":88,"f_shopicon_1":0},"2":{"f_id":2,"f_exchangeRwards":"295-1","f_PreCost":"295-1","f_PreRewards":"296-10","f_MinRate":100,"f_Specialpara1":50,"f_exchangeCost1":"294-10","f_type":1,"f_mainicon":295,"f_shopicon":296,"f_shopicon_1":0},"3":{"f_id":3,"f_exchangeRwards":"320-1","f_PreCost":"320-1","f_PreRewards":"321-10","f_MinRate":100,"f_Specialpara1":50,"f_exchangeCost1":"319-10","f_type":2,"f_mainicon":320,"f_shopicon":321,"f_shopicon_1":0},"4":{"f_id":4,"f_exchangeRwards":"502-1","f_PreCost":"502-1","f_PreRewards":"500-10","f_MinRate":100,"f_Specialpara1":50,"f_exchangeCost1":"503-10","f_type":3,"f_mainicon":502,"f_shopicon":500,"f_shopicon_1":501},"5":{"f_id":5,"f_exchangeRwards":"506-1","f_PreCost":"506-1","f_PreRewards":"507-10","f_MinRate":100,"f_Specialpara1":50,"f_exchangeCost1":"505-10","f_type":4,"f_mainicon":506,"f_shopicon":507,"f_shopicon_1":0},"6":{"f_id":6,"f_exchangeRwards":"542-1","f_PreCost":"542-1","f_PreRewards":"543-10","f_MinRate":100,"f_Specialpara1":50,"f_exchangeCost1":"541-10","f_type":5,"f_mainicon":542,"f_shopicon":543,"f_shopicon_1":0}}}